{
  "position": null,
  "orders": [],
  "cycle": 395,
  "price": 3979.82,
  "signal": "HOLD",
  "confidence": 0,
  "reason": "Trend: DOWN | RSI: 38.2 | \u0e23\u0e2d Signal \u0e17\u0e35\u0e48\u0e0a\u0e31\u0e14\u0e02\u0e36\u0e49\u0e19",
  "rsi": 38.2,
  "trend": "DOWN",
  "ema_fast": 3981.35,
  "ema_slow": 3984.03,
  "atr": 2.5056,
  "sl": 3947.98,
  "tp": 4051.46,
  "balance_usdt": 9.57e-06,
  "balance_xaut": 0.0,
  "open_position": null,
  "last_update": "2026-07-17 02:51 ICT",
  "last_daily": "2026-07-15"
}